deepmirror/__init__.py
deepmirror/api.py
deepmirror/cli.py
deepmirror/config.py
deepmirror/utils.py
deepmirror-0.0.10.dist-info/licenses/LICENSE
deepmirror-0.0.10.dist-info/METADATA
deepmirror-0.0.10.dist-info/WHEEL
deepmirror-0.0.10.dist-info/entry_points.txt
deepmirror-0.0.10.dist-info/top_level.txt
deepmirror-0.0.10.dist-info/RECORD
