Metadata-Version: 2.4
Name: deepmirror
Version: 0.0.10
Summary: Command line interface for the deepmirror public API
Author-email: Ryan Greenhalgh <ryan@deepmirror.ai>
Maintainer-email: Ryan Greenhalgh <ryan@deepmirror.ai>
Project-URL: Homepage, https://www.deepmirror.ai/
Project-URL: Repository, https://github.com/deepmirror/deepmirror-client
Project-URL: Documentation, https://github.com/deepmirror/deepmirror-client
Project-URL: Issues, https://github.com/deepmirror/deepmirror-client/issues
Requires-Python: >=3.10
License-File: LICENSE
Requires-Dist: click>=8.1.8
Requires-Dist: requests>=2.31.0
Requires-Dist: httpx==0.28.1
Requires-Dist: pandas>=2.2.2
Requires-Dist: pydantic>=2.11.5
Requires-Dist: pydantic-settings>=2.9.1
Requires-Dist: scikit-learn>=1.6.1
Requires-Dist: matplotlib>=3.10.3
Requires-Dist: tqdm>=4.67.1
Requires-Dist: ipykernel>=6.29.5
Requires-Dist: types-requests==2.32.4.20250913
Requires-Dist: py3Dmol>=2.5.0
Requires-Dist: onnx>=1.18.0
Requires-Dist: rdkit==2025.3.5
Requires-Dist: strenum>=0.4.15; python_version < "3.11"
Provides-Extra: dev
Requires-Dist: pytest>=8.0.0; extra == "dev"
Requires-Dist: pre-commit>=3.6.0; extra == "dev"
Requires-Dist: pylint>=3.3.7; extra == "dev"
Requires-Dist: ruff>=0.11.13; extra == "dev"
Requires-Dist: mypy==1.18.2; extra == "dev"
Requires-Dist: types-tqdm==4.67.0.20250809; extra == "dev"
Requires-Dist: pandas-stubs==2.3.0.250703; extra == "dev"
Dynamic: license-file
